Workbook

Sheet Cover
B1: PayPal (PYPL) — FCFE perpetuity valuation
B2: One of 18 stocks valued for a hedged US–Korea–Japan portfolio. Prices 22–28 Sep 2026. Not investment advice.
B4: Prepared by | C4: Jung Ryul Lee
B5: Data as of | C5: Prices 22–28 Sep 2026
B6: Units | C6: US$ billions unless per share
B8: What this model does
B9: Free cash flow to equity valued as a growing perpetuity: FCFE × (1 + g) / (cost of equity − g).
B10: Also shows the FCFE yield and the growth rate the current price implies.
B12: Key outputs (live links)
B13: Value per share | C13: =DCF!B18 -> 77.203419
B14: Share price | C14: =DCF!B19 -> 55.04
B15: Upside / (downside) | C15: =DCF!B20 -> 0.40267839
B16: Cost of equity | C16: =DCF!B10 -> 0.10495
B17: Clears the portfolio's 15% hurdle | C17: =IF(DCF!B20>=Assumptions!B13,"Yes","No") -> Yes
B18: Held in the portfolio | C18: No
B20: Contents
B21: DCF | C21: Inputs, projection, valuation and sensitivity
B22: Assumptions | C22: Shared market inputs: risk-free rate, equity risk premium, terminal growth; model guard-rails
B24: Colour code
B25: 1,234 Blue text: hard-coded input
B26: 1,234 Black text: formula
B27: 1,234 Green text: link to another sheet
B28: Shaded yellow: key assumption to flex
B29: Shaded green: key output
B31: Method notes and limitations
B32: • Inputs come from company filings and market-data pages cited in the portfolio memo (not included).
B33: • Market inputs are shared with the other 17 models so valuations are comparable across stocks.
B35: Disclaimer
B36: Built from public information for training and portfolio purposes. Not investment advice and not a recommendation to buy or sell any security. Figures marked approximate should be checked against the original filings.

Sheet DCF
A1: PayPal (PYPL)
A2: FCFE perpetuity: value = FCFE × (1 + g) / (cost of equity − g)
A3: Inputs: company filings and market data as cited in the portfolio memo (not included) (Tickzen, Stock Titan, company guidance); prices 22–26 Sep 2026. $ in billions unless per share.
A5: Inputs
A6: Share price ($) | B6: 55.04
A7: Beta | B7: 1.17
A8: Risk-free rate | B8: =Assumptions!$B$5 -> 0.0523
A9: Equity risk premium | B9: =Assumptions!$C$5 -> 0.045
A10: Cost of equity | B10: =B8+B7*B9 -> 0.10495 | C10: CAPM
A11: Free cash flow to equity ($bn) | B11: 5.6
A12: Perpetual growth | B12: 0.015
A13: Shares (bn) | B13: 0.81849564 | C13: Market cap ÷ price at data date
C14: FY25 FCF $5.6bn (~12% yield); 1.5% growth
A16: Valuation
A17: Equity value ($bn) | B17: =B11*(1+B12)/(B10-B12) -> 63.190661
A18: Value per share ($) | B18: =B17/B13 -> 77.203419
A19: Share price ($) | B19: =B6 -> 55.04
A20: Upside / (downside) | B20: =B18/B19-1 -> 0.40267839
A21: FCFE yield at current price | B21: =B11/(B6*B13) -> 0.12430633
A22: Implied growth at current price | B22: =(B10*B6*B13-B11)/(B6*B13+B11) -> -0.017216239
A24: Sensitivity: value per share ($)
A25: Cost of equity ↓ / growth → | B25: 0 | C25: 0.015 | D25: 0.03
A26: =B10+(-0.01) -> 0.09495 | B26: =$B$11*(1+B$25)/($A26-B$25)/$B$13 -> 72.057085 | C26: =$B$11*(1+C$25)/($A26-C$25)/$B$13 -> 86.859881 | D26: =$B$11*(1+D$25)/($A26-D$25)/$B$13 -> 108.5
A27: =B10+(0) -> 0.10495 | B27: =$B$11*(1+B$25)/($A27-B$25)/$B$13 -> 65.191236 | C27: =$B$11*(1+C$25)/($A27-C$25)/$B$13 -> 77.203419 | D27: =$B$11*(1+D$25)/($A27-D$25)/$B$13 -> 94.02368
A28: =B10+(0.01) -> 0.11495 | B28: =$B$11*(1+B$25)/($A28-B$25)/$B$13 -> 59.519967 | C28: =$B$11*(1+C$25)/($A28-C$25)/$B$13 -> 69.479215 | D28: =$B$11*(1+D$25)/($A28-D$25)/$B$13 -> 82.95556

Sheet Assumptions
A1: Market assumptions (CAPM)
A2: Blue = hardcoded input. Every model sheet links here (green), so changing a cell below re-values every stock in that market.
A4: Market | B4: Risk-free rate | C4: Equity risk premium | D4: Terminal growth | E4: Source / note
A5: US | B5: 0.0523 | C5: 0.045 | D5: 0.03 | E5: US 10-yr Treasury 5.23% (Washington Trust weekly review, 25 Sep 2026); ERP and terminal growth are author assumptions
A6: KR | B6: 0.0441 | C6: 0.055 | D6: 0.025 | E6: Korea 10-yr KTB 4.41% (Trading Economics, Sep 2026); ERP and terminal growth are author assumptions
A7: JP | B7: 0.0307 | C7: 0.05 | D7: 0.015 | E7: JGB 10-yr 3.07% (Trading Economics, 25 Sep 2026); ERP and terminal growth are author assumptions
A9: Beta floor / cap (systematic models) | B9: 0.8 | C9: 1.6 | E9: Data-feed betas are clipped to this range so no stock gets a cost of equity far below its market's
A10: Growth cap (systematic models) | B10: 0.1 | C10: 0.6 | E10: B = max first-stage growth; C = max growth as a multiple of ROE (payout floor 40%)
A11: Growth floor | B11: -0.05
A12: ROE clip for payout (low / high) | B12: 0.08 | C12: 0.3
A13: Hurdle (min. upside to hold) | B13: 0.15
